graphlearn_torch/__init__.py
graphlearn_torch/typing.py
graphlearn_torch/py_graphlearn_torch.cpython-310-x86_64-linux-gnu.so
graphlearn_torch/partition/__init__.py
graphlearn_torch/partition/random_partitioner.py
graphlearn_torch/partition/base.py
graphlearn_torch/partition/frequency_partitioner.py
graphlearn_torch/partition/partition_book.py
graphlearn_torch/channel/__init__.py
graphlearn_torch/channel/remote_channel.py
graphlearn_torch/channel/base.py
graphlearn_torch/channel/shm_channel.py
graphlearn_torch/channel/mp_channel.py
graphlearn_torch/utils/__init__.py
graphlearn_torch/utils/units.py
graphlearn_torch/utils/singleton.py
graphlearn_torch/utils/mixin.py
graphlearn_torch/utils/exit_status.py
graphlearn_torch/utils/topo.py
graphlearn_torch/utils/tensor.py
graphlearn_torch/utils/common.py
graphlearn_torch/utils/build_glt.py
graphlearn_torch/utils/device.py
graphlearn_torch/loader/__init__.py
graphlearn_torch/loader/node_loader.py
graphlearn_torch/loader/link_loader.py
graphlearn_torch/loader/subgraph_loader.py
graphlearn_torch/loader/link_neighbor_loader.py
graphlearn_torch/loader/transform.py
graphlearn_torch/loader/neighbor_loader.py
graphlearn_torch/sampler/__init__.py
graphlearn_torch/sampler/base.py
graphlearn_torch/sampler/negative_sampler.py
graphlearn_torch/sampler/neighbor_sampler.py
graphlearn_torch/data/__init__.py
graphlearn_torch/data/dataset.py
graphlearn_torch/data/table_dataset.py
graphlearn_torch/data/feature.py
graphlearn_torch/data/graph.py
graphlearn_torch/data/vineyard_utils.py
graphlearn_torch/data/reorder.py
graphlearn_torch/data/unified_tensor.py
graphlearn_torch/distributed/__init__.py
graphlearn_torch/distributed/event_loop.py
graphlearn_torch/distributed/dist_server.py
graphlearn_torch/distributed/dist_table_dataset.py
graphlearn_torch/distributed/dist_client.py
graphlearn_torch/distributed/rpc.py
graphlearn_torch/distributed/dist_feature.py
graphlearn_torch-0.2.4.dist-info/WHEEL
graphlearn_torch-0.2.4.dist-info/top_level.txt
graphlearn_torch-0.2.4.dist-info/LICENSE
graphlearn_torch-0.2.4.dist-info/METADATA
graphlearn_torch-0.2.4.dist-info/RECORD
