Metadata-Version: 2.1
Name: graphlearn-torch
Version: 0.2.4
Summary: Graph Learning for PyTorch (GraphLearn-for-PyTorch)
Home-page: https://github.com/alibaba/graphlearn-for-pytorch
Author: GLT Team
License: UNKNOWN
Platform: UNKNOWN
Requires: torch
Requires-Python: >=3.6
License-File: LICENSE
